odoo8_addon_sale_pricelist_triple_discount-8.0.1.0.0.99.dev4-py3.8-nspkg.pth
odoo_addons/sale_pricelist_triple_discount/README.rst
odoo_addons/sale_pricelist_triple_discount/__init__.py
odoo_addons/sale_pricelist_triple_discount/__openerp__.py
odoo_addons/sale_pricelist_triple_discount/i18n/it.po
odoo_addons/sale_pricelist_triple_discount/i18n/sale_pricelist_triple_discount.pot
odoo_addons/sale_pricelist_triple_discount/model/__init__.py
odoo_addons/sale_pricelist_triple_discount/model/pricelist.py
odoo_addons/sale_pricelist_triple_discount/model/sale.py
odoo_addons/sale_pricelist_triple_discount/readme/CONFIGURE.rst
odoo_addons/sale_pricelist_triple_discount/readme/CONTRIBUTORS.rst
odoo_addons/sale_pricelist_triple_discount/readme/DESCRIPTION.rst
odoo_addons/sale_pricelist_triple_discount/readme/USAGE.rst
odoo_addons/sale_pricelist_triple_discount/static/description/icon.png
odoo_addons/sale_pricelist_triple_discount/static/description/index.html
odoo_addons/sale_pricelist_triple_discount/view/pricelist_view.xml
odoo8_addon_sale_pricelist_triple_discount-8.0.1.0.0.99.dev4.dist-info/METADATA
odoo8_addon_sale_pricelist_triple_discount-8.0.1.0.0.99.dev4.dist-info/WHEEL
odoo8_addon_sale_pricelist_triple_discount-8.0.1.0.0.99.dev4.dist-info/namespace_packages.txt
odoo8_addon_sale_pricelist_triple_discount-8.0.1.0.0.99.dev4.dist-info/top_level.txt
odoo8_addon_sale_pricelist_triple_discount-8.0.1.0.0.99.dev4.dist-info/RECORD
