Metadata-Version: 2.1
Name: odoo8-addon-sale-pricelist-triple-discount
Version: 8.0.1.0.0.99.dev4
Summary: Sale Pricelist Triple Discount
Home-page: https://github.com/OCA/sale-workflow/tree/8.0/sale_pricelist_triple_discount
Author: Agile Business Group, Odoo Community Association (OCA)
Author-email: support@odoo-community.org
License: AGPL-3
Platform: UNKNOWN
Classifier: Programming Language :: Python
Classifier: Framework :: Odoo
Classifier: Framework :: Odoo :: 8.0
Classifier: License :: OSI Approved :: GNU Affero General Public License v3
Requires-Python: ~=2.7
Requires-Dist: odoo8-addon-sale-pricelist-discount
Requires-Dist: odoo8-addon-sale-triple-discount
Requires-Dist: odoo (<9.0a,>=8.0a)
